turboself/__init__.py
turboself/consts.py
turboself/core.py
turboself-1.0.dist-info/LICENSE
turboself-1.0.dist-info/METADATA
turboself-1.0.dist-info/WHEEL
turboself-1.0.dist-info/top_level.txt
turboself-1.0.dist-info/RECORD
